abc_radio_wrapper/__init__.py
abc_radio_wrapper/abc_radio_wrapper.py
abc_radio_wrapper-0.3.0.dist-info/AUTHORS.rst
abc_radio_wrapper-0.3.0.dist-info/LICENSE
abc_radio_wrapper-0.3.0.dist-info/METADATA
abc_radio_wrapper-0.3.0.dist-info/WHEEL
abc_radio_wrapper-0.3.0.dist-info/top_level.txt
abc_radio_wrapper-0.3.0.dist-info/RECORD
