Metadata-Version: 2.1
Name: abc-radio-wrapper
Version: 0.3.0
Summary: API wrapper library for the song history of ABC radio channels
Home-page: https://github.com/MatthewBurke1995/ABC-Radio-Wrapper
Author: Matthew Burke
Author-email: mperoburke@gmail.com
License: MIT license
Keywords: abc_radio_wrapper
Platform: UNKNOWN
Classifier: Development Status :: 2 - Pre-Alpha
Classifier: Intended Audience :: Developers
Classifier: License :: OSI Approved :: MIT License
Classifier: Natural Language :: English
Classifier: Programming Language :: Python :: 3
Classifier: Programming Language :: Python :: 3.6
Classifier: Programming Language :: Python :: 3.7
Classifier: Programming Language :: Python :: 3.8
Requires-Python: >=3.6
License-File: LICENSE
License-File: AUTHORS.rst
Requires-Dist: requests (>=2.27.1)
Provides-Extra: test
Requires-Dist: mypy (>=0.991) ; extra == 'test'
Requires-Dist: types-requests (>=2.28.11.8) ; extra == 'test'
Requires-Dist: typing-extensions (>=4.4.0) ; extra == 'test'
Requires-Dist: requests (>=2.27.1) ; extra == 'test'
Requires-Dist: black (>=22.12.0) ; extra == 'test'
Requires-Dist: flake8 (>==6.0.0) ; extra == 'test'
Requires-Dist: sphinx ; extra == 'test'
Requires-Dist: sphinx-rtd-theme ; extra == 'test'
Requires-Dist: interrogate ; extra == 'test'
Requires-Dist: coverage ; extra == 'test'
Requires-Dist: isort ; extra == 'test'
